huaexcel.py
huanexus.py
huasap.py
huatools-0.1.dist-info/DESCRIPTION.rst
huatools-0.1.dist-info/METADATA
huatools-0.1.dist-info/RECORD
huatools-0.1.dist-info/WHEEL
huatools-0.1.dist-info/metadata.json
huatools-0.1.dist-info/top_level.txt
